Topsis/__init__.py
Topsis/__main__.py
topsis_rehnoor_102317137-1.0.0.dist-info/licenses/LICENSE
topsis_rehnoor_102317137-1.0.0.dist-info/METADATA
topsis_rehnoor_102317137-1.0.0.dist-info/WHEEL
topsis_rehnoor_102317137-1.0.0.dist-info/entry_points.txt
topsis_rehnoor_102317137-1.0.0.dist-info/top_level.txt
topsis_rehnoor_102317137-1.0.0.dist-info/RECORD
