Metadata-Version: 2.4
Name: Topsis-Rehnoor-102317137
Version: 1.0.0
Summary: A Python package for TOPSIS (Technique for Order Preference by Similarity to Ideal Solution) - Multi-Criteria Decision Making
Home-page: https://github.com/Rehnoor-Aulakh/Topsis-Rehnoor-102317137
Author: Rehnoor Aulakh
Author-email: aulakhrehnoor@gmail.com
Keywords: topsis,mcdm,multi-criteria decision making,decision analysis,ranking
Classifier: Programming Language :: Python :: 3
Classifier: Programming Language :: Python :: 3.7
Classifier: Programming Language :: Python :: 3.8
Classifier: Programming Language :: Python :: 3.9
Classifier: Programming Language :: Python :: 3.10
Classifier: Programming Language :: Python :: 3.11
Classifier: License :: OSI Approved :: MIT License
Classifier: Operating System :: OS Independent
Classifier: Intended Audience :: Education
Classifier: Intended Audience :: Science/Research
Classifier: Topic :: Scientific/Engineering
Requires-Python: >=3.7
License-File: LICENSE
Requires-Dist: pandas>=1.0.0
Requires-Dist: numpy>=1.18.0
Dynamic: author
Dynamic: author-email
Dynamic: classifier
Dynamic: description
Dynamic: description-content-type
Dynamic: home-page
Dynamic: keywords
Dynamic: license-file
Dynamic: requires-dist
Dynamic: requires-python
Dynamic: summary
